doc2git
