Metadata-Version: 1.1
Name: doc2git
Version: 0.1.5
Summary: Helper to commit generated documents to git
Home-page: http://jlesquembre.github.io/doc2git/
Author: José Luis Lafuente
Author-email: jlesquembre@gmail.com
License: GNU General Public License v3 (GPLv3)
Keywords: git,documentation
Platform: UNKNOWN
Classifier: Development Status :: 3 - Alpha
Classifier: Topic :: Utilities
Classifier: Intended Audience :: Developers
Classifier: License :: OSI Approved :: GNU General Public License v3 (GPLv3)
Classifier: Operating System :: OS Independent
Classifier: Programming Language :: Python
Classifier: Programming Language :: Python :: 3.3
